python_jwt/__init__.py
python_jwt-4.0.0.dist-info/LICENCE
python_jwt-4.0.0.dist-info/METADATA
python_jwt-4.0.0.dist-info/WHEEL
python_jwt-4.0.0.dist-info/top_level.txt
python_jwt-4.0.0.dist-info/RECORD
