Metadata-Version: 2.1
Name: python-jwt
Version: 4.0.0
Summary: Module for generating and verifying JSON Web Tokens
Home-page: https://github.com/davedoesdev/python-jwt
Author: David Halls
Author-email: dave@davedoesdev.com
License: MIT
Platform: UNKNOWN
Classifier: Programming Language :: Python :: 3
Classifier: Programming Language :: Python :: Implementation :: CPython
Requires-Python: >=3.6
License-File: LICENCE
